proxmoxer/__init__.py
proxmoxer/core.py
proxmoxer/backends/__init__.py
proxmoxer/backends/command_base.py
proxmoxer/backends/https.py
proxmoxer/backends/local.py
proxmoxer/backends/openssh.py
proxmoxer/backends/ssh_paramiko.py
proxmoxer/tools/__init__.py
proxmoxer/tools/tasks.py
proxmoxer-2.0.0.dist-info/LICENSE.txt
proxmoxer-2.0.0.dist-info/METADATA
proxmoxer-2.0.0.dist-info/WHEEL
proxmoxer-2.0.0.dist-info/top_level.txt
proxmoxer-2.0.0.dist-info/RECORD
