Metadata-Version: 2.1
Name: proxmoxer
Version: 2.0.0
Summary: Python Wrapper for the Proxmox 2.x API (HTTP and SSH)
Home-page: https://proxmoxer.github.io/docs/
Download-URL: http://pypi.python.org/pypi/proxmoxer
Author: Oleg Butovich
Author-email: obutovich@gmail.com
License: MIT
Keywords: proxmox,api
Classifier: Development Status :: 5 - Production/Stable
Classifier: Intended Audience :: Developers
Classifier: Intended Audience :: System Administrators
Classifier: License :: OSI Approved :: MIT License
Classifier: Operating System :: OS Independent
Classifier: Programming Language :: Python :: 2.7
Classifier: Programming Language :: Python :: 2
Classifier: Programming Language :: Python :: 3.4
Classifier: Programming Language :: Python :: 3.5
Classifier: Programming Language :: Python :: 3.6
Classifier: Programming Language :: Python :: 3.7
Classifier: Programming Language :: Python :: 3.8
Classifier: Programming Language :: Python :: 3.9
Classifier: Programming Language :: Python :: 3.10
Classifier: Programming Language :: Python :: 3
Classifier: Programming Language :: Python
Classifier: Topic :: Software Development :: Libraries :: Python Modules
Classifier: Topic :: System :: Clustering
Classifier: Topic :: System :: Monitoring
Classifier: Topic :: System :: Systems Administration
License-File: LICENSE.txt
